fgroup/__init__.py
fgroup/__main__.py
fgroup/_test.py
fgroup/file.py
fgroup/filetree.py
fgroup/formatter.py
fgroup/grouper.py
fgroup/util.py
fgroup-1.2.2.dist-info/LICENSE
fgroup-1.2.2.dist-info/METADATA
fgroup-1.2.2.dist-info/WHEEL
fgroup-1.2.2.dist-info/entry_points.txt
fgroup-1.2.2.dist-info/RECORD
