Metadata-Version: 2.1
Name: fgroup
Version: 1.2.2
Summary: A helpful cross-platorm utility for grouping files across many locations.
Home-page: https://www.mathgeniuszach.com/
License: MIT
Author: mathgeniuszach
Author-email: huntingmanzach@gmail.com
Requires-Python: >=3.8,<4.0
Classifier: License :: OSI Approved :: MIT License
Classifier: Programming Language :: Python :: 3
Classifier: Programming Language :: Python :: 3.8
Classifier: Programming Language :: Python :: 3.9
Classifier: Programming Language :: Python :: 3.10
Classifier: Programming Language :: Python :: 3.11
Classifier: Programming Language :: Python :: 3.12
Requires-Dist: pyyaml (>=6.0.0,<7.0.0)
Project-URL: Repository, https://github.com/mathgeniuszach/fgroup
